lavalink/__init__.py
lavalink/enums.py
lavalink/lavalink.py
lavalink/log.py
lavalink/node.py
lavalink/player.py
lavalink/rest_api.py
lavalink/tuples.py
lavalink/utils.py
useless_lavalink-1.4.6.dist-info/LICENSE
useless_lavalink-1.4.6.dist-info/WHEEL
useless_lavalink-1.4.6.dist-info/METADATA
useless_lavalink-1.4.6.dist-info/RECORD
