Metadata-Version: 2.1
Name: useless-lavalink
Version: 1.4.6
Summary: A fork of Red-Lavalink for useless_bot
Home-page: https://github.com/jotonedev/useless_lavalink
License: GPL-3.0-or-later
Keywords: lavalink,lavalink-client,discord,discord.py
Author: jotonedev
Author-email: mrvillager.dev@gmail.com
Maintainer: jotonedev
Maintainer-email: mrvillager.dev@gmail.com
Requires-Python: >=3.9,<4.0
Classifier: Development Status :: 5 - Production/Stable
Classifier: Framework :: aiohttp
Classifier: License :: OSI Approved :: GNU General Public License v3 or later (GPLv3+)
Classifier: Programming Language :: Python :: 3
Classifier: Programming Language :: Python :: 3.10
Classifier: Programming Language :: Python :: 3.9
Classifier: Topic :: Communications :: Chat
Classifier: Topic :: Internet
Classifier: Topic :: Multimedia :: Sound/Audio
Classifier: Topic :: Software Development :: Libraries
Classifier: Topic :: Software Development :: Libraries :: Python Modules
Classifier: Topic :: Utilities
Classifier: Typing :: Typed
Provides-Extra: docs
Requires-Dist: aiohttp
Requires-Dist: discord.py (>=1.7,<3)
Requires-Dist: sphinx (>=3.4.2,<5); extra == "docs"
Requires-Dist: sphinx-rtd-theme (>=1.0,<2.0); extra == "docs"
Requires-Dist: sphinxcontrib-trio (>=1.1.2,<2.0.0); extra == "docs"
Requires-Dist: typing-extensions (>=4.1.1,<5.0.0); extra == "docs"
Project-URL: Bug Tracker, https://github.com/jotonedev/useless_lavalink/issues
Project-URL: Documentation, https://useless-lavalink.readthedocs.io/en/stable
Project-URL: Repository, https://github.com/jotonedev/useless_lavalink
